pyhdx/__init__.py
pyhdx/__version__.py
pyhdx/_version.py
pyhdx/alignment.py
pyhdx/batch_processing.py
pyhdx/cli.py
pyhdx/config.py
pyhdx/config.yaml
pyhdx/datasets.py
pyhdx/fileIO.py
pyhdx/fit_models.py
pyhdx/fitting.py
pyhdx/fitting_torch.py
pyhdx/legacy.py
pyhdx/local_cluster.py
pyhdx/models.py
pyhdx/output.py
pyhdx/plot.py
pyhdx/process.py
pyhdx/support.py
pyhdx/tol_colors.py
pyhdx/web/__init__.py
pyhdx/web/apps.py
pyhdx/web/base.py
pyhdx/web/cache.py
pyhdx/web/constructor.py
pyhdx/web/controller_only.py
pyhdx/web/controllers.py
pyhdx/web/jinja_base.html
pyhdx/web/log.py
pyhdx/web/main_controllers.py
pyhdx/web/opts.py
pyhdx/web/pane.py
pyhdx/web/paramdoc.py
pyhdx/web/serve.py
pyhdx/web/sources.py
pyhdx/web/template.py
pyhdx/web/theme.py
pyhdx/web/tools.py
pyhdx/web/transforms.py
pyhdx/web/utils.py
pyhdx/web/views.py
pyhdx/web/widgets.py
pyhdx/web/apps/_main.py
pyhdx/web/apps/peptide_app.yaml
pyhdx/web/apps/peptide_faq.md
pyhdx/web/apps/pyhdx_app.yaml
pyhdx/web/apps/rfu_app.yaml
pyhdx/web/readme/holoviews.png
pyhdx/web/readme/molstar.png
pyhdx/web/readme/pyhdx_diagram.py
pyhdx/web/readme/pyhdx_main_application.png
pyhdx/web/readme/pyhdx_rfu.png
pyhdx/web/readme/readme.rst
pyhdx/web/readme/tables_list.txt
pyhdx/web/static/index.html
pyhdx/web/static/pyhdx_header.png
pyhdx/web/static/extendedgoldentemplate/default.css
pyhdx-0.4.5.dist-info/METADATA
pyhdx-0.4.5.dist-info/WHEEL
pyhdx-0.4.5.dist-info/entry_points.txt
pyhdx-0.4.5.dist-info/licenses/LICENSE.txt
pyhdx-0.4.5.dist-info/RECORD
