Metadata-Version: 2.4
Name: pyhdx
Version: 0.4.5
Summary: Derive ΔG for single residues from HDX-MS data
Project-URL: Source, https://github.com/Jhsmit/PyHDX/
Project-URL: Documentation, https://pyhdx.readthedocs.io/en/stable/
Author-email: Jochem Smit <jhsmit@gmail.com>
License-Expression: MIT
License-File: LICENSE.txt
Classifier: Development Status :: 4 - Beta
Classifier: Intended Audience :: Science/Research
Classifier: Natural Language :: English
Classifier: Programming Language :: Python :: 3.11
Requires-Python: <3.12,>=3.11
Requires-Dist: colorcet
Requires-Dist: dask
Requires-Dist: distributed
Requires-Dist: hdxms-datasets>=0.3.3
Requires-Dist: hdxrate
Requires-Dist: matplotlib
Requires-Dist: narwhals
Requires-Dist: numpy==1.25.2
Requires-Dist: omegaconf
Requires-Dist: packaging
Requires-Dist: pandas
Requires-Dist: param<2
Requires-Dist: pyyaml
Requires-Dist: scikit-image
Requires-Dist: scipy
Requires-Dist: symfit
Requires-Dist: torch
Requires-Dist: tqdm
Requires-Dist: typer
Requires-Dist: ultraplot
Provides-Extra: dev
Requires-Dist: black[jupyter]; extra == 'dev'
Provides-Extra: docs
Requires-Dist: mkdocs; extra == 'docs'
Requires-Dist: mkdocs-gen-files; extra == 'docs'
Requires-Dist: mkdocs-jupyter; extra == 'docs'
Requires-Dist: mkdocs-literate-nav; extra == 'docs'
Requires-Dist: mkdocs-material; extra == 'docs'
Requires-Dist: mkdocstrings[python]; extra == 'docs'
Requires-Dist: pygments; extra == 'docs'
Provides-Extra: pdf
Requires-Dist: pylatex; extra == 'pdf'
Requires-Dist: ultraplot; extra == 'pdf'
Provides-Extra: test
Requires-Dist: pytest>=7.2.0; extra == 'test'
Provides-Extra: web
Requires-Dist: bokeh==2.4.3; extra == 'web'
Requires-Dist: colorcet; extra == 'web'
Requires-Dist: holoviews==1.17.1; extra == 'web'
Requires-Dist: hvplot==0.8.4; extra == 'web'
Requires-Dist: panel==0.14.4; extra == 'web'
Requires-Dist: param<2; extra == 'web'
